podder_task_base/__init__.py
podder_task_base/config.py
podder_task_base/context.py
podder_task_base/exceptions.py
podder_task_base/file.py
podder_task_base/settings.py
podder_task_base/api/__init__.py
podder_task_base/api/grpc_server.py
podder_task_base/api/task_api_executor.py
podder_task_base/databases/__init__.py
podder_task_base/databases/pipeline.py
podder_task_base/databases/sqlalchemy_logger_setting.py
podder_task_base/log/__init__.py
podder_task_base/log/log_setting.py
podder_task_base/log/logger.py
podder_task_base/models/__init__.py
podder_task_base/models/pipeline/__init__.py
podder_task_base/models/pipeline/job_model.py
podder_task_base/models/pipeline/resource_model.py
podder_task_base/repositories/__init__.py
podder_task_base/repositories/job_repository.py
podder_task_base/repositories/resource_repository.py
podder_task_base/repositories/base/__init__.py
podder_task_base/repositories/base/base_repository.py
podder_task_base/services/__init__.py
podder_task_base/services/inputs.py
podder_task_base/services/throttle.py
podder_task_base/tasks/__init__.py
podder_task_base/tasks/base_task.py
podder_task_base/utils/__init__.py
podder_task_base/utils/string_utils.py
podder_task_base-0.9.1.dist-info/METADATA
podder_task_base-0.9.1.dist-info/WHEEL
podder_task_base-0.9.1.dist-info/top_level.txt
podder_task_base-0.9.1.dist-info/RECORD
