Metadata-Version: 2.1
Name: podder-task-base
Version: 0.9.1
Summary: UNKNOWN
Home-page: https://github.com/podder-ai/podder-task-base
Author: podder-ai
Author-email: UNKNOWN
License: UNKNOWN
Platform: UNKNOWN
Requires-Dist: grpcio-tools (==1.18.0)
Requires-Dist: googleapis-common-protos (==1.6.0)
Requires-Dist: mysqlclient (==1.4.1)
Requires-Dist: SQLAlchemy (==1.3.3)
Requires-Dist: python-dotenv (==0.10.1)
Requires-Dist: click (==7.0)
Requires-Dist: jinja2 (==2.10.1)
Requires-Dist: PyYAML (==5.1)
Requires-Dist: pytest (==4.3.1)
Requires-Dist: requests (==2.22.0)
